xhs_auto_mcp/__init__.py
xhs_auto_mcp/main.py
xhs_auto_mcp/tools/log_utils.py
xhs_auto_mcp/tools/write_xiaohongshu.py
xhs_auto_mcp/tools/xhs_api.py
xhs_auto_mcp/tools/xhsvm.js
xhs_auto_mcp-0.1.1.dist-info/METADATA
xhs_auto_mcp-0.1.1.dist-info/WHEEL
xhs_auto_mcp-0.1.1.dist-info/entry_points.txt
xhs_auto_mcp-0.1.1.dist-info/top_level.txt
xhs_auto_mcp-0.1.1.dist-info/RECORD
