Metadata-Version: 2.4
Name: xhs-auto-mcp
Version: 0.1.1
Summary: 小红书自动化工具mcp服务器，提供小红书内容发布及交互功能
Author: fancybooi999
License-Expression: MIT
Classifier: Programming Language :: Python :: 3
Classifier: Programming Language :: Python :: 3.12
Classifier: Operating System :: OS Independent
Requires-Python: >=3.12
Requires-Dist: curl-cffi>=0.10.0
Requires-Dist: mcp[cli]>=1.6.0
Requires-Dist: fastmcp>=2.10.4
Requires-Dist: pyexecjs>=1.5.1
Requires-Dist: requests>=2.32.3
Requires-Dist: selenium>=4.34.2
Requires-Dist: loguru>=0.7.2
Requires-Dist: python-dotenv>=1.1.1
Requires-Dist: fastapi>=0.110.0
Requires-Dist: uvicorn>=0.34.2
Provides-Extra: dev
Requires-Dist: build>=1.2.2.post1; extra == "dev"
Requires-Dist: setuptools>=45; extra == "dev"
Requires-Dist: twine>=6.1.0; extra == "dev"
